{"width":1024,"SubTexture":[{"width":274,"y":1951,"height":74,"name":"arm","x":1},{"width":836,"y":580,"height":469,"name":"body","x":1},{"width":254,"y":1442,"height":243,"name":"bra","x":1},{"width":234,"y":1687,"height":247,"name":"face","x":1},{"width":841,"y":1,"height":577,"name":"hair","x":1},{"width":294,"y":1051,"height":389,"name":"pet","x":1},{"width":208,"y":1687,"height":262,"name":"arm1","x":237},{"width":166,"y":1442,"height":178,"name":"loading_bg_maozi","x":257}],"height":2048,"name":"loading_girl","imagePath":"loading_girl_tex.png"}